[
    {
        "label": "Chrysler Sebring Convertible 2010",
        "prob": "1.0"
    },
    {
        "label": "Ford Focus Sedan 2007",
        "prob": "0.2842"
    },
    {
        "label": "Dodge Dakota Club Cab 2007",
        "prob": "0.8163"
    },
    {
        "label": "Audi S4 Sedan 2007",
        "prob": "0.9675"
    },
    {
        "label": "BMW 1 Series Coupe 2012",
        "prob": "1.0"
    },
    {
        "label": "GMC Yukon Hybrid SUV 2012",
        "prob": "0.9733"
    },
    {
        "label": "Honda Odyssey Minivan 2012",
        "prob": "0.9999"
    },
    {
        "label": "Mitsubishi Lancer Sedan 2012",
        "prob": "0.9996"
    },
    {
        "label": "smart fortwo Convertible 2012",
        "prob": "0.9961"
    },
    {
        "label": "Toyota Sequoia SUV 2012",
        "prob": "0.9993"
    },
    {
        "label": "BMW Z4 Convertible 2012",
        "prob": "0.9759"
    },
    {
        "label": "FIAT 500 Convertible 2012",
        "prob": "1.0"
    },
    {
        "label": "Ford F-450 Super Duty Crew Cab 2012",
        "prob": "1.0"
    },
    {
        "label": "Ford Fiesta Sedan 2012",
        "prob": "0.978"
    },
    {
        "label": "Buick Rainier SUV 2007",
        "prob": "0.9999"
    },
    {
        "label": "Honda Accord Coupe 2012",
        "prob": "0.9988"
    },
    {
        "label": "Dodge Ram Pickup 3500 Crew Cab 2010",
        "prob": "0.9907"
    },
    {
        "label": "Eagle Talon Hatchback 1998",
        "prob": "0.9845"
    },
    {
        "label": "Aston Martin V8 Vantage Convertible 2012",
        "prob": "0.9953"
    },
    {
        "label": "Bentley Arnage Sedan 2009",
        "prob": "0.9933"
    },
    {
        "label": "AM General Hummer SUV 2000",
        "prob": "0.9991"
    },
    {
        "label": "BMW M5 Sedan 2010",
        "prob": "0.9992"
    },
    {
        "label": "Jaguar XK XKR 2012",
        "prob": "0.9999"
    },
    {
        "label": "Dodge Charger Sedan 2012",
        "prob": "0.9836"
    },
    {
        "label": "Chrysler Aspen SUV 2009",
        "prob": "0.9899"
    },
    {
        "label": "Spyker C8 Coupe 2009",
        "prob": "1.0"
    },
    {
        "label": "Chevrolet Express Cargo Van 2007",
        "prob": "0.9373"
    },
    {
        "label": "HUMMER H3T Crew Cab 2010",
        "prob": "0.4933"
    },
    {
        "label": "Maybach Landaulet Convertible 2012",
        "prob": "0.5507"
    },
    {
        "label": "Spyker C8 Convertible 2009",
        "prob": "1.0"
    },
    {
        "label": "Land Rover LR2 SUV 2012",
        "prob": "0.9998"
    },
    {
        "label": "Chevrolet Corvette ZR1 2012",
        "prob": "0.9985"
    },
    {
        "label": "Aston Martin Virage Coupe 2012",
        "prob": "0.9116"
    },
    {
        "label": "Ferrari 458 Italia Coupe 2012",
        "prob": "0.6424"
    },
    {
        "label": "Audi S4 Sedan 2012",
        "prob": "0.3464"
    },
    {
        "label": "Scion xD Hatchback 2012",
        "prob": "0.9961"
    },
    {
        "label": "Dodge Charger SRT-8 2009",
        "prob": "0.9933"
    },
    {
        "label": "Acura RL Sedan 2012",
        "prob": "0.9967"
    },
    {
        "label": "Chevrolet Silverado 1500 Extended Cab 2012",
        "prob": "0.9882"
    },
    {
        "label": "Chevrolet Silverado 1500 Extended Cab 2012",
        "prob": "0.9731"
    },
    {
        "label": "Hyundai Accent Sedan 2012",
        "prob": "0.9925"
    },
    {
        "label": "Volkswagen Beetle Hatchback 2012",
        "prob": "0.9991"
    },
    {
        "label": "Toyota Corolla Sedan 2012",
        "prob": "0.8845"
    },
    {
        "label": "Ford F-450 Super Duty Crew Cab 2012",
        "prob": "0.2599"
    },
    {
        "label": "Chrysler PT Cruiser Convertible 2008",
        "prob": "0.9997"
    },
    {
        "label": "Dodge Dakota Crew Cab 2010",
        "prob": "0.9991"
    },
    {
        "label": "Chrysler PT Cruiser Convertible 2008",
        "prob": "1.0"
    },
    {
        "label": "Chevrolet Camaro Convertible 2012",
        "prob": "0.9934"
    },
    {
        "label": "Audi S5 Coupe 2012",
        "prob": "0.9181"
    },
    {
        "label": "Audi TT Hatchback 2011",
        "prob": "0.9999"
    },
    {
        "label": "Dodge Journey SUV 2012",
        "prob": "0.9999"
    },
    {
        "label": "Chevrolet Monte Carlo Coupe 2007",
        "prob": "0.4114"
    },
    {
        "label": "Daewoo Nubira Wagon 2002",
        "prob": "0.9951"
    },
    {
        "label": "Mercedes-Benz C-Class Sedan 2012",
        "prob": "0.9978"
    },
    {
        "label": "Suzuki Kizashi Sedan 2012",
        "prob": "0.233"
    },
    {
        "label": "Chevrolet Camaro Convertible 2012",
        "prob": "0.4003"
    },
    {
        "label": "Dodge Charger Sedan 2012",
        "prob": "0.96"
    },
    {
        "label": "BMW M6 Convertible 2010",
        "prob": "0.9914"
    },
    {
        "label": "Suzuki SX4 Hatchback 2012",
        "prob": "0.9809"
    },
    {
        "label": "Audi S4 Sedan 2007",
        "prob": "0.9841"
    },
    {
        "label": "Audi TT RS Coupe 2012",
        "prob": "0.9908"
    },
    {
        "label": "Ford Focus Sedan 2007",
        "prob": "0.9939"
    },
    {
        "label": "Land Rover Range Rover SUV 2012",
        "prob": "0.4025"
    },
    {
        "label": "Audi S6 Sedan 2011",
        "prob": "0.9933"
    },
    {
        "label": "Ford GT Coupe 2006",
        "prob": "1.0"
    },
    {
        "label": "Acura TSX Sedan 2012",
        "prob": "0.9967"
    },
    {
        "label": "Ford Edge SUV 2012",
        "prob": "0.9829"
    },
    {
        "label": "Buick Enclave SUV 2012",
        "prob": "0.9981"
    },
    {
        "label": "Honda Accord Sedan 2012",
        "prob": "0.9992"
    },
    {
        "label": "Rolls-Royce Phantom Drophead Coupe Convertible 2012",
        "prob": "0.9942"
    },
    {
        "label": "Nissan 240SX Coupe 1998",
        "prob": "0.7659"
    },
    {
        "label": "Bentley Continental GT Coupe 2012",
        "prob": "0.9974"
    },
    {
        "label": "Chevrolet Malibu Hybrid Sedan 2010",
        "prob": "0.868"
    },
    {
        "label": "Bentley Continental GT Coupe 2012",
        "prob": "0.7358"
    },
    {
        "label": "Ram C/V Cargo Van Minivan 2012",
        "prob": "0.9959"
    },
    {
        "label": "Ford Edge SUV 2012",
        "prob": "0.9996"
    },
    {
        "label": "Cadillac SRX SUV 2012",
        "prob": "0.8611"
    },
    {
        "label": "Cadillac SRX SUV 2012",
        "prob": "0.9731"
    },
    {
        "label": "Chevrolet Malibu Sedan 2007",
        "prob": "0.883"
    },
    {
        "label": "Geo Metro Convertible 1993",
        "prob": "0.9972"
    },
    {
        "label": "Dodge Magnum Wagon 2008",
        "prob": "0.9899"
    },
    {
        "label": "Suzuki Aerio Sedan 2007",
        "prob": "1.0"
    },
    {
        "label": "Jeep Grand Cherokee SUV 2012",
        "prob": "0.9999"
    },
    {
        "label": "Chevrolet HHR SS 2010",
        "prob": "0.9981"
    },
    {
        "label": "BMW X3 SUV 2012",
        "prob": "1.0"
    },
    {
        "label": "Fisker Karma Sedan 2012",
        "prob": "0.9984"
    },
    {
        "label": "Infiniti QX56 SUV 2011",
        "prob": "0.9999"
    },
    {
        "label": "Ford F-150 Regular Cab 2007",
        "prob": "0.9998"
    },
    {
        "label": "Mercedes-Benz 300-Class Convertible 1993",
        "prob": "0.9994"
    },
    {
        "label": "Mitsubishi Lancer Sedan 2012",
        "prob": "0.9549"
    },
    {
        "label": "BMW M5 Sedan 2010",
        "prob": "0.8234"
    },
    {
        "label": "Chrysler 300 SRT-8 2010",
        "prob": "0.9648"
    },
    {
        "label": "Cadillac SRX SUV 2012",
        "prob": "0.9992"
    },
    {
        "label": "GMC Yukon Hybrid SUV 2012",
        "prob": "0.9997"
    },
    {
        "label": "Acura Integra Type R 2001",
        "prob": "0.9995"
    },
    {
        "label": "Nissan 240SX Coupe 1998",
        "prob": "1.0"
    },
    {
        "label": "Acura ZDX Hatchback 2012",
        "prob": "0.5658"
    },
    {
        "label": "BMW M5 Sedan 2010",
        "prob": "0.854"
    },
    {
        "label": "Ford Ranger SuperCab 2011",
        "prob": "0.4111"
    },
    {
        "label": "Lamborghini Diablo Coupe 2001",
        "prob": "0.9999"
    }
]